[
    {
       "id":1,
       "name":"Axis Midcap Direct Plan Growth",
       "fundType":"Equity",
       "morningStar":5,
       "risk":"Moderately High",
       "nav":"Rs.35.5 (31-Mar-2020)",
       "isin":"IN10005003",
       "fundStartDate":"01-Jan-13",
       "fundSize":"Rs.5,193Cr",
       "fundManager":"Shreyash Devalkar",
       "minPurchaseAmt":"Rs.1000",
       "oneYear":"-9.40%",
       "threeYears":"6.70%",
       "fiveYears":"6.60%",
       "topFive":"21.00%",
       "topFiveHoldings":[
          "Avenue Supermarts Ltd. - 5.5%",
          "City Union Bank Ltd. - 3.9%",
          "Bata India Ltd. - 3.9%",
          "Voltas Ltd. - 3.8%",
          "Astral Poly Technik Ltd. - 3.5%"
       ],
       "pros":[
          "1. Risk is lower compared to the benchmark",
          "2. Lower expense ratio",
          "3. 1Y Returns are higher than the benchmark",
          "4. 3Y Returns are higher than the benchmark"
       ],
       "cons":[
          "1. Asset under management(AUM) is more than 5000 Crs. Returns tend to go low once AUM exceeds a certain amount",
          "2. Risk-adjusted returns are lower compared to the category",
          "3. 5Y Returns are lower than the benchmark"
       ]
    },
    {
       "id":2,
       "name":"L&T Midcap Fund Direct Growth",
       "fundType":"Equity",
       "morningStar":4,
       "risk":"High",
       "nav":"Rs.105.0 (31-Mar-2020)",
       "isin":"IN10005006",
       "fundStartDate":"01-Jan-2013",
       "fundSize":"Rs.6,213Cr",
       "fundManager":"Venugopal Manghat",
       "minPurchaseAmt":"Rs.500",
       "oneYear":"-26.4%",
       "threeYears":"-4.60%",
       "fiveYears":"3.70%",
       "topFive":"13.00%",
       "topFiveHoldings":[
          "City Union Bank Ltd. - 2.7%",
          "Cholamandalam Investment & Finance Co. Ltd. - 2.6%",
          "Ipca Laboratories Ltd. - 2.5%",
          "Bayer CropScience Ltd. - 2.5%",
          "Shree Cement Ltd. - 2.5%"
       ],
       "pros":[
          "1. Risk is lower compared to the benchmark",
          "2. Lower expense ratio",
          "3. 1Y Returns are higher than the benchmark"
       ],
       "cons":[
          "1. Asset under management(AUM) is more than 5000 Crs. Returns tend to go low once AUM exceeds a certain amount",
          "2. Risk-adjusted returns are lower compared to the category",
          "3. 3Y Returns are lower than the benchmark",
          "4. 5Y Returns are lower than the benchmark"
       ]
    },
    {
       "id":3,
       "name":"HDFC Mid Cap Opportunities Direct Plan Growth",
       "fundType":"Equity",
       "morningStar":3,
       "risk":"Moderately High",
       "nav":"Rs.41.5 (31-Mar-2020)",
       "isin":"IN10005999",
       "fundStartDate":"01-Jan-13",
       "fundSize":"Rs.23,788Cr",
       "fundManager":"Chirag Setalvad",
       "minPurchaseAmt":"Rs.500",
       "oneYear":"-30.00%",
       "threeYears":"-7.00%",
       "fiveYears":"2.10%",
       "topFive":"19.00%",
       "topFiveHoldings":[
          "Cholamandalam Investment & Finance Co. Ltd. - 4.5%",
          "Aarti Industries Ltd. - 3.9%",
          "Balkrishna Industries Ltd. - 3.8%",
          "City Union Bank Ltd. - 3.2%",
          "Sundram Fasteners Ltd. - 3.2%"
       ],
       "pros":[
          "1. Risk is lower compared to the benchmark",
          "2. Lower expense ratio",
          "3. 1Y Returns are higher than the benchmark"
       ],
       "cons":[
          "1. Asset under management(AUM) is more than 5000 Crs. Returns tend to go low once AUM exceeds a certain amount",
          "2. Risk-adjusted returns are lower compared to the category",
          "3. 3Y Returns are lower than the benchmark",
          "4. 5Y Returns are lower than the benchmark"
       ]
    },
    {
       "id":4,
       "name":"DSP Midcap Direct Plan Growth",
       "fundType":"Equity",
       "morningStar":4,
       "risk":"Moderately High",
       "nav":"Rs.47.0 (31-Mar-2020)",
       "isin":"IN10005664",
       "fundStartDate":"01-Jan-13",
       "fundSize":"Rs.7,458Cr",
       "fundManager":"Vinit Sambre",
       "minPurchaseAmt":"Rs.500",
       "oneYear":"-18.20%",
       "threeYears":"2.50%",
       "fiveYears":"5.20%",
       "topFive":"21.00%",
       "topFiveHoldings":[
          "Avenue Supermarts Ltd. - 5.5",
          "City Union Bank Ltd. - 3.9%",
          "Bata India Ltd. - 3.9%",
          "Voltas Ltd. - 3.8%",
          "Astral Poly Technik Ltd. - 3.5%"
       ],
       "pros":[
          "1. Risk is lower compared to the benchmark",
          "2. Lower expense ratio",
          "3. 1Y Returns are higher than the benchmark"
       ],
       "cons":[
          "1. Asset under management(AUM) is more than 5000 Crs. Returns tend to go low once AUM exceeds a certain amount",
          "2. Risk-adjusted returns are lower compared to the category",
          "3. 3Y Returns are lower than the benchmark",
          "4. 5Y Returns are lower than the benchmark"
       ]
    }
]